felling/README.md
felling/__init__.py
felling/__main__.py
felling/compare_logs.py
felling/configure_felling.py
felling/email.py
felling/resources/logger.json
felling-0.1.6.dist-info/METADATA
felling-0.1.6.dist-info/WHEEL
felling-0.1.6.dist-info/licenses/LICENSE
felling-0.1.6.dist-info/RECORD
