Metadata-Version: 2.3
Name: felling
Version: 0.1.6
Summary: A simple package to easily create consistent logs
Project-URL: Source, https://github.com/this-josh/felling
Project-URL: Tracker, https://github.com/this-josh/felling/issues
Author-email: Josh Kirk <felling@joshkirk.co.uk>
License: MIT
License-File: LICENSE
Keywords: log,logging,logs
Classifier: Development Status :: 4 - Beta
Classifier: License :: OSI Approved :: MIT License
Classifier: Operating System :: OS Independent
Classifier: Programming Language :: Python :: 3
Requires-Python: >=3.10
